{
    "id": 323, 
    "name": "Zodiark", 
    "filename": "323_zodiark", 
    "special_attack": "Chain Burst", 
    "stats": {
        "normal": {
            "speed": 40, 
            "attack": 10, 
            "hit_rate": 100, 
            "mblock": 0, 
            "evade": 100, 
            "defense": 200, 
            "mdef": 120, 
            "mpow": 16, 
            "hp": 7777, 
            "mp": 3000, 
            "gil": 650, 
            "exp": 3181, 
            "level": 56, 
            "immunity": [
                "Poison", 
                "Pig", 
                "Near fatal", 
                "Berserk", 
                "Confuse", 
                "Psyche"
            ], 
            "status": [
                "Reflect"
            ], 
            "absorb": [
                "Fire"
            ], 
            "null": [], 
            "weakness": [
                "Ice", 
                "Water"
            ], 
            "misc": [
                "Dies at 0 MP", 
                "Human"
            ], 
            "metamorph_rate": "25%", 
            "special_attack_effect": "4.5x damage", 
            "special_attack_flags": []
        }, 
        "hard": {
            "speed": 45, 
            "attack": 13, 
            "hit_rate": 100, 
            "mblock": 0, 
            "evade": 100, 
            "defense": 200, 
            "mdef": 120, 
            "mpow": 17, 
            "hp": 8888, 
            "mp": 3200, 
            "gil": 715, 
            "exp": 3519, 
            "level": 57, 
            "immunity": [
                "Poison", 
                "Pig", 
                "Near fatal", 
                "Berserk", 
                "Confuse", 
                "Psyche"
            ], 
            "status": [
                "Reflect"
            ], 
            "absorb": [
                "Fire"
            ], 
            "null": [], 
            "weakness": [
                "Ice", 
                "Water"
            ], 
            "misc": [
                "Dies at 0 MP", 
                "Hard to run from"
            ], 
            "metamorph_rate": "25%", 
            "special_attack_effect": "4.5x damage", 
            "special_attack_flags": []
        }, 
        "extreme": {
            "speed": 50, 
            "attack": 16, 
            "hit_rate": 100, 
            "mblock": 0, 
            "evade": 100, 
            "defense": 200, 
            "mdef": 120, 
            "mpow": 18, 
            "hp": 9999, 
            "mp": 3400, 
            "gil": 786, 
            "exp": 4474, 
            "level": 58, 
            "immunity": [
                "Poison", 
                "Pig", 
                "Near fatal", 
                "Berserk", 
                "Confuse", 
                "Psyche"
            ], 
            "status": [
                "Reflect"
            ], 
            "absorb": [
                "Fire"
            ], 
            "null": [], 
            "weakness": [
                "Ice", 
                "Water"
            ], 
            "misc": [
                "Dies at 0 MP", 
                "Hard to run from"
            ], 
            "metamorph_rate": "25%", 
            "special_attack_effect": "4.5x damage", 
            "special_attack_flags": []
        }, 
        "insane": {
            "speed": 55, 
            "attack": 19, 
            "hit_rate": 110, 
            "mblock": 0, 
            "evade": 100, 
            "defense": 200, 
            "mdef": 120, 
            "mpow": 21, 
            "hp": 10999, 
            "mp": 3600, 
            "gil": 865, 
            "exp": 5590, 
            "level": 61, 
            "immunity": [
                "Poison", 
                "Pig", 
                "Near fatal", 
                "Berserk", 
                "Confuse", 
                "Psyche"
            ], 
            "status": [
                "Reflect"
            ], 
            "absorb": [
                "Fire"
            ], 
            "null": [], 
            "weakness": [
                "Ice", 
                "Water"
            ], 
            "misc": [
                "Dies at 0 MP", 
                "Hard to run from"
            ], 
            "metamorph_rate": "25%", 
            "special_attack_effect": "4.5x damage", 
            "special_attack_flags": []
        }
    }, 
    "loots": {
        "steal_rare": {
            "id": 155, 
            "name": "Magic Tab"
        }, 
        "steal_common": {
            "id": 235, 
            "name": "Ether"
        }, 
        "drop_rare": {
            "id": 235, 
            "name": "Ether"
        }, 
        "drop_common": {
            "id": 255, 
            "name": "Nothing"
        }
    }, 
    "spirits": {
        "spirit_a": {
            "id": 149, 
            "name": "Level 4 Flare"
        }, 
        "spirit_b": {
            "id": 0, 
            "name": "Fireball"
        }
    }, 
    "inverses": {
        "inverse_a": {
            "id": 9, 
            "name": "Inferno"
        }, 
        "inverse_b": {
            "id": 10, 
            "name": "Blizzard"
        }
    }, 
    "torments": {
        "torment_a": {
            "id": 238, 
            "name": "Attack"
        }, 
        "torment_b": {
            "id": 9, 
            "name": "Inferno"
        }, 
        "torment_c": {
            "id": 10, 
            "name": "Blizzard"
        }, 
        "torment_d": {
            "id": 11, 
            "name": "Nova"
        }
    }, 
    "fight_animation": {
        "id": 255, 
        "name": "Nothing"
    }, 
    "metamorph": {
        "id": 14, 
        "metamorph_a": {
            "id": 233, 
            "name": "Potion"
        }, 
        "metamorph_b": {
            "id": 233, 
            "name": "Potion"
        }, 
        "metamorph_c": {
            "id": 233, 
            "name": "Potion"
        }, 
        "metamorph_d": {
            "id": 238, 
            "name": "Elixir"
        }
    }
}